teamaker/__init__.py
teamaker/gameengine.py
teamaker-0.0.1.dist-info/LICENSE
teamaker-0.0.1.dist-info/METADATA
teamaker-0.0.1.dist-info/WHEEL
teamaker-0.0.1.dist-info/top_level.txt
teamaker-0.0.1.dist-info/RECORD
