Metadata-Version: 2.1
Name: teamaker
Version: 0.0.1
Summary: Minimal game engine to create and play text-edit adventures
Home-page: https://github.com/gmargari/teamaker
Author: Giorgos Margaritis
Author-email: gmargari@protonmail.com
License: MIT
Project-URL: Bug Tracker, https://github.com/gmargari/teamaker/issues
Platform: UNKNOWN
Classifier: Development Status :: 2 - Pre-Alpha
Classifier: Programming Language :: Python :: 3.6
Classifier: Programming Language :: Python :: 3.7
Classifier: Programming Language :: Python :: 3.8
Classifier: Programming Language :: Python :: 3.9
Classifier: License :: OSI Approved :: MIT License
Classifier: Operating System :: OS Independent
Requires-Python: >=3.6
License-File: LICENSE
Requires-Dist: Cerberus
Requires-Dist: overrides
Requires-Dist: watchdog
